LICENSE.txt
MANIFEST.in
README.rst
setup.py
examples/asmexport.py
examples/copypools.py
examples/createnode.py
examples/createucs.py
examples/deletenode.py
examples/deletepools.py
examples/f5mku.py
examples/listnodes.py
examples/modifynode.py
examples/modifypool.py
examples/newnode.py
examples/testlarge.py
examples/testmodule.py
examples/testtoken.py
examples/upload.py
iCR/__init__.py
iCR/iCR.py
iCR.egg-info/PKG-INFO
iCR.egg-info/SOURCES.txt
iCR.egg-info/dependency_links.txt
iCR.egg-info/requires.txt
iCR.egg-info/top_level.txt