Metadata-Version: 1.0
Name: iCR
Version: 2.3
Summary: This is a Python module to easily use the F5 iControl REST interface
Home-page: https://pypi.python.org/pypi?:action=display&name=iCR&version=2.3
Author: Pete White
Author-email: pwhite@f5.com
License: PSF
Platform: UNKNOWN
